{
  "catalogue": "CRT-SC",
  "generated_at": "2025-12-25T18:57:50+00:00",
  "source_csv": "apps/data_sources/crt_catalogues/CRT-SC.csv",
  "records": [
    {
      "﻿vendor_id": "SC-0001",
      "service_type": "IaaS",
      "dependency_type": "direct",
      "criticality": "high",
      "region": "global",
      "contract_tier": "enhanced",
      "data_access_level": "full",
      "failure_modes": "outage;identity-failure",
      "vendor_archetype": "Cloud Infrastructure Provider (IaaS)",
      "example_vendors": "AWS; Azure; DigitalOcean",
      "notes": "Primary cloud platform",
      "source_ref": "baseline",
      "mapped_control_ids": "CRT-C-0018; CRT-C-0065; CRT-C-0049; CRT-C-0040; CRT-C-0026; CRT-C-0030"
    },
    {
      "﻿vendor_id": "SC-0002",
      "service_type": "IaaS",
      "dependency_type": "direct",
      "criticality": "high",
      "region": "global",
      "contract_tier": "enhanced",
      "data_access_level": "full",
      "failure_modes": "outage",
      "vendor_archetype": "Cloud Infrastructure Provider (IaaS)",
      "example_vendors": "AWS; Azure; DigitalOcean",
      "notes": "Alternative cloud tenancy",
      "source_ref": "baseline",
      "mapped_control_ids": "CRT-C-0018; CRT-C-0065; CRT-C-0049; CRT-C-0040; CRT-C-0026"
    },
    {
      "﻿vendor_id": "SC-0003",
      "service_type": "SaaS",
      "dependency_type": "direct",
      "criticality": "medium",
      "region": "global",
      "contract_tier": "standard",
      "data_access_level": "limited",
      "failure_modes": "auth-failure",
      "vendor_archetype": "Cloud Productivity & Collaboration Suite",
      "example_vendors": "Google Workspace; Office 365",
      "notes": "Business productivity suite",
      "source_ref": "baseline",
      "mapped_control_ids": "CRT-C-0007; CRT-C-0012; CRT-C-0009; CRT-C-0026; CRT-C-0022; CRT-C-0039"
    },
    {
      "﻿vendor_id": "SC-0004",
      "service_type": "SaaS",
      "dependency_type": "direct",
      "criticality": "medium",
      "region": "global",
      "contract_tier": "standard",
      "data_access_level": "limited",
      "failure_modes": "auth-failure",
      "vendor_archetype": "Cloud Productivity & Collaboration Suite",
      "example_vendors": "Google Workspace; Office 365",
      "notes": "Email & collaboration",
      "source_ref": "baseline",
      "mapped_control_ids": "CRT-C-0007; CRT-C-0012; CRT-C-0009; CRT-C-0026; CRT-C-0039; CRT-C-0031"
    },
    {
      "﻿vendor_id": "SC-0005",
      "service_type": "SaaS",
      "dependency_type": "direct",
      "criticality": "medium",
      "region": "US",
      "contract_tier": "standard",
      "data_access_level": "full",
      "failure_modes": "data-leak",
      "vendor_archetype": "CRM & Customer Engagement Platform",
      "example_vendors": "Salesforce",
      "notes": "CRM and customer data",
      "source_ref": "baseline",
      "mapped_control_ids": "CRT-C-0039; CRT-C-0026; CRT-C-0022; CRT-C-0027; CRT-C-0025"
    },
    {
      "﻿vendor_id": "SC-0006",
      "service_type": "SaaS",
      "dependency_type": "direct",
      "criticality": "high",
      "region": "US",
      "contract_tier": "regulated",
      "data_access_level": "limited",
      "failure_modes": "api-failure; payment-failure",
      "vendor_archetype": "Payment Processor / PSP",
      "example_vendors": "PCI Payment Vendor MSP; Stripe",
      "notes": "Payment processor",
      "source_ref": "baseline",
      "mapped_control_ids": "CRT-C-0039; CRT-C-0026; CRT-C-0025; CRT-C-0042; CRT-C-0041"
    },
    {
      "﻿vendor_id": "SC-0007",
      "service_type": "SaaS",
      "dependency_type": "direct",
      "criticality": "high",
      "region": "global",
      "contract_tier": "enhanced",
      "data_access_level": "full",
      "failure_modes": "identity-outage",
      "vendor_archetype": "Identity & Access Platform (IDaaS)",
      "example_vendors": "Okta",
      "notes": "Identity provider alternative",
      "source_ref": "baseline",
      "mapped_control_ids": "CRT-C-0009; CRT-C-0007; CRT-C-0012; CRT-C-0011; CRT-C-0049; CRT-C-0065"
    },
    {
      "﻿vendor_id": "SC-0008",
      "service_type": "SaaS",
      "dependency_type": "indirect",
      "criticality": "low",
      "region": "US",
      "contract_tier": "standard",
      "data_access_level": "none",
      "failure_modes": "outage; email-failure",
      "vendor_archetype": "Email Delivery Service",
      "example_vendors": "SendGrid",
      "notes": "Transactional email",
      "source_ref": "baseline",
      "mapped_control_ids": "CRT-C-0026; CRT-C-0025; CRT-C-0027; CRT-C-0040"
    },
    {
      "﻿vendor_id": "SC-0009",
      "service_type": "SaaS",
      "dependency_type": "direct",
      "criticality": "medium",
      "region": "US",
      "contract_tier": "standard",
      "data_access_level": "limited",
      "failure_modes": "code-exposure",
      "vendor_archetype": "Code Hosting & Repository Platform",
      "example_vendors": "GitHub",
      "notes": "Source control",
      "source_ref": "baseline",
      "mapped_control_ids": "CRT-C-0022; CRT-C-0026; CRT-C-0039; CRT-C-0049; CRT-C-0065"
    },
    {
      "﻿vendor_id": "SC-0010",
      "service_type": "SaaS",
      "dependency_type": "indirect",
      "criticality": "medium",
      "region": "global",
      "contract_tier": "enhanced",
      "data_access_level": "limited",
      "failure_modes": "ddos-bypass; waf-failure",
      "vendor_archetype": "Edge Security & CDN Provider",
      "example_vendors": "Akamai; Cloudflare",
      "notes": "WAF & CDN",
      "source_ref": "baseline",
      "mapped_control_ids": "CRT-C-0023; CRT-C-0016; CRT-C-0049; CRT-C-0027; CRT-C-0026"
    },
    {
      "﻿vendor_id": "SC-0011",
      "service_type": "IaaS",
      "dependency_type": "direct",
      "criticality": "medium",
      "region": "EU",
      "contract_tier": "standard",
      "data_access_level": "full",
      "failure_modes": "outage",
      "vendor_archetype": "Cloud Infrastructure Provider (IaaS)",
      "example_vendors": "AWS; Azure; DigitalOcean",
      "notes": "Secondary infrastructure",
      "source_ref": "baseline",
      "mapped_control_ids": "CRT-C-0018; CRT-C-0065; CRT-C-0049; CRT-C-0040; CRT-C-0026"
    },
    {
      "﻿vendor_id": "SC-0012",
      "service_type": "SaaS",
      "dependency_type": "indirect",
      "criticality": "low",
      "region": "global",
      "contract_tier": "standard",
      "data_access_level": "none",
      "failure_modes": "outage",
      "vendor_archetype": "Work Management / Issue Tracking",
      "example_vendors": "Jira",
      "notes": "Project management",
      "source_ref": "baseline",
      "mapped_control_ids": "CRT-C-0026; CRT-C-0027; CRT-C-0022; CRT-C-0039"
    },
    {
      "﻿vendor_id": "SC-0013",
      "service_type": "SaaS",
      "dependency_type": "indirect",
      "criticality": "low",
      "region": "global",
      "contract_tier": "standard",
      "data_access_level": "limited",
      "failure_modes": "outage",
      "vendor_archetype": "Team Collaboration & Messaging",
      "example_vendors": "Slack",
      "notes": "Collaboration tool",
      "source_ref": "baseline",
      "mapped_control_ids": "CRT-C-0007; CRT-C-0012; CRT-C-0026; CRT-C-0027; CRT-C-0039"
    },
    {
      "﻿vendor_id": "SC-0014",
      "service_type": "SaaS",
      "dependency_type": "direct",
      "criticality": "high",
      "region": "global",
      "contract_tier": "enhanced",
      "data_access_level": "full",
      "failure_modes": "telemetry-loss",
      "vendor_archetype": "Observability & Telemetry Platform",
      "example_vendors": "Datadog; New Relic",
      "notes": "Monitoring and observability",
      "source_ref": "baseline",
      "mapped_control_ids": "CRT-C-0049; CRT-C-0026; CRT-C-0027; CRT-C-0040"
    },
    {
      "﻿vendor_id": "SC-0015",
      "service_type": "SaaS",
      "dependency_type": "direct",
      "criticality": "high",
      "region": "global",
      "contract_tier": "enhanced",
      "data_access_level": "limited",
      "failure_modes": "telemetry-loss",
      "vendor_archetype": "Observability & Telemetry Platform",
      "example_vendors": "Datadog; New Relic",
      "notes": "APM service",
      "source_ref": "baseline",
      "mapped_control_ids": "CRT-C-0049; CRT-C-0026; CRT-C-0027"
    },
    {
      "﻿vendor_id": "SC-0016",
      "service_type": "SaaS",
      "dependency_type": "direct",
      "criticality": "high",
      "region": "global",
      "contract_tier": "enhanced",
      "data_access_level": "full",
      "failure_modes": "indexing-failure",
      "vendor_archetype": "Security Analytics & SIEM Platform",
      "example_vendors": "Splunk",
      "notes": "SIEM ingestion",
      "source_ref": "baseline",
      "mapped_control_ids": "CRT-C-0049; CRT-C-0052; CRT-C-0026; CRT-C-0027; CRT-C-0040"
    },
    {
      "﻿vendor_id": "SC-0017",
      "service_type": "SaaS",
      "dependency_type": "direct",
      "criticality": "medium",
      "region": "US",
      "contract_tier": "standard",
      "data_access_level": "limited",
      "failure_modes": "outage",
      "vendor_archetype": "IT Service Management Platform",
      "example_vendors": "ServiceNow",
      "notes": "Incident & workflow",
      "source_ref": "baseline",
      "mapped_control_ids": "CRT-C-0026; CRT-C-0022; CRT-C-0027; CRT-C-0039"
    },
    {
      "﻿vendor_id": "SC-0018",
      "service_type": "SaaS",
      "dependency_type": "indirect",
      "criticality": "medium",
      "region": "US",
      "contract_tier": "standard",
      "data_access_level": "none",
      "failure_modes": "api-failure",
      "vendor_archetype": "Communications Platform (CPaaS)",
      "example_vendors": "Twilio",
      "notes": "Messaging/OTP provider",
      "source_ref": "baseline",
      "mapped_control_ids": "CRT-C-0026; CRT-C-0025; CRT-C-0027; CRT-C-0039"
    },
    {
      "﻿vendor_id": "SC-0019",
      "service_type": "SaaS",
      "dependency_type": "indirect",
      "criticality": "medium",
      "region": "global",
      "contract_tier": "enhanced",
      "data_access_level": "limited",
      "failure_modes": "ddos-bypass",
      "vendor_archetype": "Edge Security & CDN Provider",
      "example_vendors": "Akamai; Cloudflare",
      "notes": "Edge delivery network",
      "source_ref": "baseline",
      "mapped_control_ids": "CRT-C-0023; CRT-C-0016; CRT-C-0049; CRT-C-0027; CRT-C-0026"
    },
    {
      "﻿vendor_id": "SC-0020",
      "service_type": "MSP",
      "dependency_type": "transitive",
      "criticality": "high",
      "region": "UK",
      "contract_tier": "regulated",
      "data_access_level": "full",
      "failure_modes": "data-exposure",
      "vendor_archetype": "Payment Processor / PSP",
      "example_vendors": "PCI Payment Vendor MSP; Stripe",
      "notes": "Handles regulated payment flows",
      "source_ref": "baseline",
      "mapped_control_ids": "CRT-C-0039; CRT-C-0026; CRT-C-0025; CRT-C-0041; CRT-C-0042"
    },
    {
      "﻿vendor_id": "SC-0021",
      "service_type": "IaaS",
      "dependency_type": "direct",
      "criticality": "high",
      "region": "EU",
      "contract_tier": "standard",
      "data_access_level": "full",
      "failure_modes": "facility-failure",
      "vendor_archetype": "Regional Data Centre Provider",
      "example_vendors": "Regional Data Centre",
      "notes": "Secondary hosting",
      "source_ref": "baseline",
      "mapped_control_ids": "CRT-C-0055; CRT-C-0058; CRT-C-0060; CRT-C-0018; CRT-C-0026"
    },
    {
      "﻿vendor_id": "SC-0022",
      "service_type": "Consultancy",
      "dependency_type": "indirect",
      "criticality": "low",
      "region": "UK",
      "contract_tier": "standard",
      "data_access_level": "none",
      "failure_modes": "",
      "vendor_archetype": "Penetration Testing Provider",
      "example_vendors": "Penetration Testing Provider",
      "notes": "Security testing",
      "source_ref": "baseline",
      "mapped_control_ids": "CRT-C-0026; CRT-C-0025; CRT-C-0027"
    },
    {
      "﻿vendor_id": "SC-0023",
      "service_type": "SaaS",
      "dependency_type": "indirect",
      "criticality": "high",
      "region": "EU",
      "contract_tier": "enhanced",
      "data_access_level": "limited",
      "failure_modes": "backup-failure",
      "vendor_archetype": "Backup-as-a-Service Provider",
      "example_vendors": "Backup-as-a-Service",
      "notes": "Resilience function",
      "source_ref": "baseline",
      "mapped_control_ids": "CRT-C-0062; CRT-C-0060; CRT-C-0026; CRT-C-0027"
    },
    {
      "﻿vendor_id": "SC-0024",
      "service_type": "SaaS",
      "dependency_type": "indirect",
      "criticality": "medium",
      "region": "EU",
      "contract_tier": "standard",
      "data_access_level": "limited",
      "failure_modes": "filtering-failure",
      "vendor_archetype": "Email Security & Filtering Gateway",
      "example_vendors": "Email Filtering Gateway",
      "notes": "Email security gateway",
      "source_ref": "baseline",
      "mapped_control_ids": "CRT-C-0023; CRT-C-0026; CRT-C-0027; CRT-C-0049"
    },
    {
      "﻿vendor_id": "SC-0025",
      "service_type": "SaaS",
      "dependency_type": "transitive",
      "criticality": "medium",
      "region": "EU",
      "contract_tier": "standard",
      "data_access_level": "limited",
      "failure_modes": "data-leak",
      "vendor_archetype": "External Analytics & Insights Provider",
      "example_vendors": "External Analytics Vendor",
      "notes": "Analytics processing",
      "source_ref": "baseline",
      "mapped_control_ids": "CRT-C-0039; CRT-C-0026; CRT-C-0025; CRT-C-0027"
    }
  ]
}